twittertennis/__init__.py
twittertennis/handler.py
twittertennis/handler_utils.py
twittertennis/tennis_utils.py
twittertennis-0.1.2.dist-info/LICENSE
twittertennis-0.1.2.dist-info/METADATA
twittertennis-0.1.2.dist-info/WHEEL
twittertennis-0.1.2.dist-info/top_level.txt
twittertennis-0.1.2.dist-info/RECORD
