Metadata-Version: 2.1
Name: twittertennis
Version: 0.1.2
Summary: Utility packages for Twitter tennis tournaments data sets.
Home-page: https://github.com/ferencberes/twittertennis
Author: Ferenc Beres
Author-email: fberes@info.ilab.sztaki.hu
License: UNKNOWN
Keywords: graph,dynamic graph,temporal network,mention graph,twitter
Platform: UNKNOWN
Requires-Python: >=3.6
Requires-Dist: networkx
Requires-Dist: pandas
Requires-Dist: datetime
Requires-Dist: pytz
Requires-Dist: matplotlib
Requires-Dist: seaborn
Requires-Dist: tqdm
